pugsql/__init__.py
pugsql/compiler.py
pugsql/context.py
pugsql/exceptions.py
pugsql/lexer.py
pugsql/parser.py
pugsql/statement.py
pugsql-0.3.7.dist-info/METADATA
pugsql-0.3.7.dist-info/WHEEL
pugsql-0.3.7.dist-info/licenses/LICENSE
pugsql-0.3.7.dist-info/RECORD
