Metadata-Version: 2.4
Name: pugsql
Version: 0.3.7
Summary: PugSQL is an anti-ORM that facilitates interacting with databases using SQL in files.
License: Apache-2.0
License-File: LICENSE
Author: Dan McKinley
Author-email: mcfunley@gmail.com
Requires-Python: >=3.9
Classifier: Development Status :: 4 - Beta
Classifier: Intended Audience :: Developers
Classifier: License :: OSI Approved :: Apache Software License
Classifier: Operating System :: OS Independent
Classifier: Programming Language :: Python :: 3
Classifier: Programming Language :: Python :: 3.9
Classifier: Programming Language :: Python :: 3.10
Classifier: Programming Language :: Python :: 3.11
Classifier: Programming Language :: Python :: 3.12
Classifier: Programming Language :: Python :: 3.13
Classifier: Programming Language :: Python :: 3.14
Classifier: Topic :: Database :: Front-Ends
Requires-Dist: sqlalchemy (>=2.0.31)
Project-URL: Homepage, https://pugsql.org
Project-URL: Repository, https://github.com/mcfunley/pugsql
